MANIFEST.in
Makefile
README.md
requirements.txt
setup.py
ReseaSDK.egg-info/PKG-INFO
ReseaSDK.egg-info/SOURCES.txt
ReseaSDK.egg-info/dependency_links.txt
ReseaSDK.egg-info/requires.txt
ReseaSDK.egg-info/top_level.txt
bin/reseasdk
reseasdk/__init__.py
reseasdk/defines.py
reseasdk/helpers.py
reseasdk/main.py
reseasdk/package.py
reseasdk/run.py
reseasdk/validators.py
reseasdk/version.py
reseasdk/commands/__init__.py
reseasdk/commands/build.py
reseasdk/commands/clean.py
reseasdk/commands/help.py
reseasdk/commands/log.py
reseasdk/commands/new.py
reseasdk/commands/run.py
reseasdk/commands/scaffold.py
reseasdk/commands/test.py
reseasdk/commands/version.py