Metadata-Version: 1.1
Name: ReseaSDK
Version: 0.4.0
Summary: A software development kit for Resea
Home-page: http://resea.net
Author: Seiya Nuta
Author-email: nuta@seiya.me
License: Public Domain
Platform: UNKNOWN
Classifier: Development Status :: 2 - Pre-Alpha
Classifier: Intended Audience :: Developers
Classifier: License :: Public Domain
Classifier: Programming Language :: Python :: 3
